setup.cfg
setup.py
alacarte/__init__.py
alacarte/core.py
alacarte/engines.py
alacarte/release.py
alacarte/resolver.py
alacarte/util.py
alacarte.egg-info/PKG-INFO
alacarte.egg-info/SOURCES.txt
alacarte.egg-info/dependency_links.txt
alacarte.egg-info/entry_points.txt
alacarte.egg-info/namespace_packages.txt
alacarte.egg-info/top_level.txt
alacarte.egg-info/zip-safe
alacarte/serialize/__init__.py
alacarte/serialize/bencode.py
alacarte/serialize/json_.py
alacarte/serialize/marshal_.py
alacarte/serialize/pickle_.py
alacarte/serialize/yaml_.py
alacarte/template/__init__.py
alacarte/template/cheetah_.py
alacarte/template/engine.py
alacarte/template/formatter.py
alacarte/template/genshi_.py
alacarte/template/jinja2_.py
alacarte/template/mako_.py
alacarte/template/sprintf.py
alacarte/template/template.py
cti/__init__.py
cti/core.py
cti/engines.py
cti/middleware.py
cti/release.py
cti/resolver.py
cti/serializers/__init__.py
cti/templating/__init__.py