Metadata-Version: 1.0
Name: alacarte
Version: 0.6.2
Summary: A common templating interface for Python applications.
Home-page: http://github.com/GothAlice/alacarte/
Author: Alice Bevan-McGregor
Author-email: alice@gothcandy.com
License: MIT
Download-URL: http://cheeseshop.python.org/pypi/alacarte/
Platform: UNKNOWN
Classifier: Development Status :: 4 - Beta
Classifier: Environment :: Console
Classifier: Intended Audience :: Developers
Classifier: License :: OSI Approved :: MIT License
Classifier: Operating System :: OS Independent
Classifier: Programming Language :: Python
Classifier: Topic :: Software Development :: Libraries :: Python Modules
